shellwhat/State.py
shellwhat/__init__.py
shellwhat/checks.py
shellwhat/sct_syntax.py
shellwhat/test_exercise.py
shellwhat-0.0.1.dist-info/DESCRIPTION.rst
shellwhat-0.0.1.dist-info/METADATA
shellwhat-0.0.1.dist-info/RECORD
shellwhat-0.0.1.dist-info/WHEEL
shellwhat-0.0.1.dist-info/metadata.json
shellwhat-0.0.1.dist-info/top_level.txt
