Metadata-Version: 2.0
Name: shellwhat
Version: 0.0.1
Summary: Submission correctness tests for shell languages
Home-page: https://github.com/datacamp/shellwhat
Author: Michael Chow
Author-email: michael@datacamp.com
License: UNKNOWN
Platform: UNKNOWN
Requires-Dist: sqlwhat
